secret_lib/__init__.py
secret_lib/env_file.py
secret_lib/environ.py
secret_lib/exceptions.py
secret_lib/hsc_vault.py
secret_lib/secret_interface.py
secret_lib-0.1.1.dist-info/METADATA
secret_lib-0.1.1.dist-info/WHEEL
secret_lib-0.1.1.dist-info/top_level.txt
secret_lib-0.1.1.dist-info/RECORD
