Metadata-Version: 2.1
Name: secret_lib
Version: 0.1.1
Summary: A wrapper for different configuration/secret sources.
Home-page: https://github.com/smileservices/secret_lib
Author: vladimir gorea
Author-email: vladimir@smileservices.dev
Classifier: Programming Language :: Python :: 3
Classifier: License :: OSI Approved :: MIT License
Classifier: Operating System :: OS Independent
Requires-Python: >=3.6
Requires-Dist: hvac
Requires-Dist: python-dotenv
